PieIsReal-3.0.dist-info/DESCRIPTION.rst
PieIsReal-3.0.dist-info/METADATA
PieIsReal-3.0.dist-info/RECORD
PieIsReal-3.0.dist-info/WHEEL
PieIsReal-3.0.dist-info/dependency_links.txt
PieIsReal-3.0.dist-info/metadata.json
PieIsReal-3.0.dist-info/top_level.txt
pieisreal/__init__.py
pieisreal/beginners.py
pieisreal/boards.py
pieisreal/color.py
pieisreal/games.py
