Metadata-Version: 2.0
Name: PieIsReal
Version: 3.0
Summary: PieIsReal is a python learning framework forked from LiveWires. Significantly modified for python 3 compatibility
Home-page: UNKNOWN
Author: Richard Crook, Gareth McCaughan, Paul Wright, Rhodri James, Neil Turton, Centric Web Estate (Daniel J Holmes)
Author-email: opensource@centricwebestate.com
License: UNKNOWN
Platform: UNKNOWN
Provides-Extra: pygame
Requires-Dist: pygame (>=1.9.2); extra == 'pygame'
